__main__.py
completions.py
core.cpython-38-x86_64-linux-gnu.so
error_handler.py
formatters.py
llm.py
models.py
shell.py
ui.py
utils.py
shell_llm-0.1.8.dist-info/METADATA
shell_llm-0.1.8.dist-info/WHEEL
shell_llm-0.1.8.dist-info/entry_points.txt
shell_llm-0.1.8.dist-info/top_level.txt
shell_llm-0.1.8.dist-info/RECORD
